venv_management/__init__.py
venv_management/api.py
venv_management/driver.py
venv_management/environment.py
venv_management/errors.py
venv_management/extension.py
venv_management/pyenv_config.py
venv_management/shell.py
venv_management/utilities.py
venv_management/version.py
venv_management/ext/__init__.py
venv_management/ext/drivers/__init__.py
venv_management/ext/drivers/pyenv_virtualenv/__init__.py
venv_management/ext/drivers/pyenv_virtualenv/driver.py
venv_management/ext/drivers/venv/__init__.py
venv_management/ext/drivers/venv/driver.py
venv_management/ext/drivers/virtualenv_sh/__init__.py
venv_management/ext/drivers/virtualenv_sh/driver.py
venv_management/ext/drivers/virtualenvwrapper/__init__.py
venv_management/ext/drivers/virtualenvwrapper/driver.py
venv_management-3.0.1.dist-info/LICENSE.txt
venv_management-3.0.1.dist-info/METADATA
venv_management-3.0.1.dist-info/WHEEL
venv_management-3.0.1.dist-info/entry_points.txt
venv_management-3.0.1.dist-info/top_level.txt
venv_management-3.0.1.dist-info/zip-safe
venv_management-3.0.1.dist-info/RECORD
