Metadata-Version: 2.1
Name: venv-management
Version: 3.0.1
Summary: A Python package for programmatic creation of Python virtual environments
Home-page: https://github.com/sixty-north/venv-management
Author: Sixty North AS
Author-email: systems+venv_management@sixty-north.com
License: MIT License
Keywords: virtual-environment
Classifier: Development Status :: 5 - Production/Stable
Classifier: Topic :: Scientific/Engineering
Classifier: License :: OSI Approved :: MIT License
Classifier: Programming Language :: Python :: 3 :: Only
Classifier: Programming Language :: Python :: 3.7
Classifier: Programming Language :: Python :: 3.8
Classifier: Programming Language :: Python :: 3.9
License-File: LICENSE.txt
Requires-Dist: stevedore
Provides-Extra: dev
Requires-Dist: bumpversion ; extra == 'dev'
Provides-Extra: doc
Requires-Dist: sphinx ; extra == 'doc'
Requires-Dist: sphinx-rtd-theme ; extra == 'doc'
Requires-Dist: better-apidoc ; extra == 'doc'
Requires-Dist: six ; extra == 'doc'
Provides-Extra: test
Requires-Dist: pytest ; extra == 'test'
